BioSAK/BLCA_op_parser.py
BioSAK/BioSAK_config.py
BioSAK/COG2020.py
BioSAK/COG2024.py
BioSAK/COG_boxplot_last1row.R
BioSAK/COG_boxplot_last2row.R
BioSAK/CheckM.py
BioSAK/Combine_KEGG_COG.py
BioSAK/Combine_KEGG_arCOG.py
BioSAK/DendroDF.py
BioSAK/DnaFeaturesViewer.py
BioSAK/FastaSplitler_by_num.py
BioSAK/FastaSplitler_by_size.py
BioSAK/FasterqDump.py
BioSAK/GTDB_for_BLCA.py
BioSAK/GenBank.py
BioSAK/Gene2Ctg.py
BioSAK/KEGG.py
BioSAK/KEGG_boxplot_last1row.R
BioSAK/KEGG_get_eukaryotic_kos.py
BioSAK/KeepRemovingTmp.py
BioSAK/MeanMappingDepth.py
BioSAK/MetaCHIP_phylo.hmm
BioSAK/MetaCyc_reactions_with_ec.txt
BioSAK/NetEnzymes.py
BioSAK/Prodigal.py
BioSAK/Reads_simulator.py
BioSAK/RunGraphMB.py
BioSAK/SILVA_for_BLCA.py
BioSAK/SankeyTaxon.py
BioSAK/SubsampleLongReads.py
BioSAK/Tax4Fun2IndOTU.py
BioSAK/UNITE_for_BLCA.py
BioSAK/Usearch16S.py
BioSAK/VERSION
BioSAK/VisBlastOp.py
BioSAK/VisGeneFlk.py
BioSAK/__init__.py
BioSAK/abd.backup.py
BioSAK/abd.py
BioSAK/abd_16s_amplicon.py
BioSAK/abd_16s_metagenome.py
BioSAK/abd_mask.py
BioSAK/abd_rename_and_combine.py
BioSAK/abund.py
BioSAK/add_desc.py
BioSAK/arCOG.py
BioSAK/bam2reads.py
BioSAK/blast.py
BioSAK/blca.py
BioSAK/blca_generate_abundance_table.py
BioSAK/blca_main.py
BioSAK/blca_subset_db_acc.py
BioSAK/blca_subset_db_gg.py
BioSAK/boxplot.py
BioSAK/boxplot_last1row.R
BioSAK/boxplot_matrix_COG.py
BioSAK/boxplot_matrix_COG_backup.py
BioSAK/boxplot_matrix_KEGG.py
BioSAK/boxplot_matrix_dbCAN.py
BioSAK/cat_fa.py
BioSAK/cdb.py
BioSAK/cdb_to_itol_piechart.py
BioSAK/cdd2cog.pl
BioSAK/checkm_marker.py
BioSAK/combine_fun_stats.py
BioSAK/combine_low_abd_otu.py
BioSAK/compare.py
BioSAK/count_num.py
BioSAK/cross_link_seqs.py
BioSAK/dbCAN.py
BioSAK/download_GenBank_genome_subset_prokaryotes_csv.py
BioSAK/enrich.py
BioSAK/exe_cmds.py
BioSAK/ezaai2mat.py
BioSAK/fa2id.py
BioSAK/fastaai.py
BioSAK/format_converter.py
BioSAK/fq2fa.py
BioSAK/gapseq.py
BioSAK/gbk2faa.py
BioSAK/gbk2ffn.py
BioSAK/gbk2fna.py
BioSAK/gbk2gff.py
BioSAK/gbk_to_ffn_faa.py
biosak-1.127.13.dist-info/LICENSE
biosak-1.127.13.dist-info/METADATA
biosak-1.127.13.dist-info/WHEEL
biosak-1.127.13.dist-info/top_level.txt
biosak-1.127.13.dist-info/RECORD
