Metadata-Version: 2.1
Name: biosak
Version: 1.127.13
Summary: BioSAK
Home-page: https://github.com/songweizhi/BioSAK
Author: Weizhi Song
Author-email: songwz03@gmail.com
License: GPL3+
Keywords: Bioinformatics
License-File: LICENSE
Requires-Dist: biopython
Requires-Dist: matplotlib
Requires-Dist: numpy
Requires-Dist: scipy
Requires-Dist: itolapi
Requires-Dist: networkx
Requires-Dist: seaborn
Requires-Dist: lxml
Requires-Dist: beautifulsoup4
Requires-Dist: ete3
Requires-Dist: statsmodels
